nordicdata/__init__.py
nordicdata-0.0.0.dist-info/METADATA
nordicdata-0.0.0.dist-info/WHEEL
nordicdata-0.0.0.dist-info/top_level.txt
nordicdata-0.0.0.dist-info/RECORD
