Metadata-Version: 2.1
Name: nordicdata
Version: 0.0.0
Summary: Coming soon
Author-email: Ruben Selander <ruben.selander@nordicintel.com>
